[1,["6dfvUfO89JVLpouC0NJdz/@6c48a"],["_textureSource"],["cc.SpriteFrame"],0,[{"name":"shuibei2","rect":{"x":2,"y":2,"width":174,"height":316},"offset":{"x":-39,"y":96},"originalSize":{"width":256,"height":512},"rotated":false,"capInsets":[0,0,0,0],"vertices":{"rawPosition":[-87,-158,0,87,-158,0,-87,158,0,87,158,0],"indexes":[0,1,2,2,1,3],"uv":[2,510,176,510,2,194,176,194],"nuv":[0.0078125,0.37890625,0.6875,0.37890625,0.0078125,0.99609375,0.6875,0.99609375],"minPos":{"x":-87,"y":-158,"z":0},"maxPos":{"x":87,"y":158,"z":0}},"packable":true,"pixelsToUnit":100,"pivot":{"x":0.5,"y":0.5},"meshType":0}],[0],0,[0],[0],[0]]
